jpaye/__init__.py
jpaye/cmd.py
jpaye/jcpy/__init__.py
jpaye/jcpy/redirect_stream.py
jpaye/libs/__init__.py
jpaye/libs/jcpy_engine.so
jpaye/libs/jcpy_loader.so
jpaye-0.0.2.dist-info/LICENSE
jpaye-0.0.2.dist-info/METADATA
jpaye-0.0.2.dist-info/WHEEL
jpaye-0.0.2.dist-info/entry_points.txt
jpaye-0.0.2.dist-info/top_level.txt
jpaye-0.0.2.dist-info/RECORD
