Metadata-Version: 2.1
Name: jpaye
Version: 0.0.2
Summary: Python Lib Locator
Author-email: Hanh Nguyen <hanhnguyenvan@gmail.com>
Maintainer-email: Hanh Nguyen <hanhnguyenvan@gmail.com>
License: MIT License
Project-URL: Homepage, https://github.com/hahn80/jpaye
Project-URL: Bug Tracker, https://github.com/hahn80/jpaye/issues
Keywords: Python,Library,Locator
Classifier: Programming Language :: Python :: 3
Classifier: License :: OSI Approved :: MIT License
Classifier: Programming Language :: Cython
Classifier: Operating System :: POSIX :: Linux
Requires-Python: >=3.10
License-File: LICENSE
Provides-Extra: test
Requires-Dist: pytest; extra == "test"
Requires-Dist: faker; extra == "test"
